CHANGES.txt
LICENSE.txt
MANIFEST.in
README.txt
setup.py
js/__init__.py
js.lightbox.egg-info/PKG-INFO
js.lightbox.egg-info/SOURCES.txt
js.lightbox.egg-info/dependency_links.txt
js.lightbox.egg-info/entry_points.txt
js.lightbox.egg-info/namespace_packages.txt
js.lightbox.egg-info/not-zip-safe
js.lightbox.egg-info/requires.txt
js.lightbox.egg-info/top_level.txt
js/lightbox/__init__.py
js/lightbox/test_lightbox.txt
js/lightbox/resources/css/lightbox.css
js/lightbox/resources/img/lightbox-blank.gif
js/lightbox/resources/img/lightbox-btn-close.gif
js/lightbox/resources/img/lightbox-btn-next.gif
js/lightbox/resources/img/lightbox-btn-prev.gif
js/lightbox/resources/img/lightbox-ico-loading.gif
js/lightbox/resources/js/lightbox.js
js/lightbox/resources/js/lightbox.min.js