Metadata-Version: 1.0
Name: js.lightbox
Version: 0.1.1
Summary: fanstatic jquery lightbox.
Home-page: https://github.com/amleczko/js.lightbox
Author: Andrew Mleczko
Author-email: andrew@mleczko.net
License: GPL
Keywords: fanstatic jquery lightbox
Platform: UNKNOWN
